samples/sdi/crc8.sv
// Stand-in for the opaque cell `gate.u_crc`. The sample SDI models u_crc as a
// black box (no `unit`, `blackBox: true`) — this file exists only so the sample
// can be simulated to produce a trace.
module crc8 (
  input  logic [7:0] data,
  output logic [7:0] crc
);
  assign crc = {data[6:0], 1'b0} ^ (data[7] ? 8'h07 : 8'h00);
endmodule

samples/sdi/gate.sv
// Sample design for the Riptide SDI schema (see docs/sdi.md).
// Two lanes of a small packet gate. Deliberately exercises every axis the
// schema exists for: an enum, a packed struct, an unpacked memory, a
// parameterized module, a generate loop, a black box, control dependence,
// a dynamic index, and a read-only assertion.

package pkt_pkg;
  // Lane state. VCD would report this as a plain 2-bit reg.
  typedef enum logic [1:0] {
    IDLE = 2'd0,
    BUSY = 2'd1,
    DONE = 2'd3
  } state_e;

  // Packed header. VCD would report this as one 12-bit vector.
  typedef struct packed {
    logic [7:0] payload;
    logic [2:0] len;
    logic       last;
  } pkt_t;
endpackage

module lane
  import pkt_pkg::*;
#(
  parameter int unsigned W = 8
) (
  input  logic         clk,
  input  logic         rst_n,   // active-low reset
  input  logic         start,
  input  logic [W-1:0] din,
  output state_e       state,
  output logic [W-1:0] dout
);
  state_e       nxt;
  logic [W-1:0] acc;

  always_comb begin
    nxt = state;
    if (state == IDLE && start) nxt = BUSY;
    else if (state == BUSY)     nxt = DONE;
    else if (state == DONE)     nxt = IDLE;
  end

  always_ff @(posedge clk or negedge rst_n) begin
    if (!rst_n) state <= IDLE;
    else        state <= nxt;
  end

  always_ff @(posedge clk) begin
    if (state == BUSY) acc <= acc + din;
  end

  assign dout = acc;
endmodule

module gate
  import pkt_pkg::*;
(
  input  logic        clk,
  input  logic        rst_n,
  input  logic        start,
  input  logic [7:0]  din,
  input  logic [1:0]  wptr,
  output logic [15:0] sum,
  output logic [11:0] hdr_out
);
  state_e     st       [2];
  logic [7:0] lane_out [2];
  pkt_t       hdr;
  logic [7:0] mem      [0:3];
  logic [7:0] crc;

  for (genvar i = 0; i < 2; i++) begin : g_lane
    lane #(.W(8)) u_lane (
      .clk   (clk),
      .rst_n (rst_n),
      .start (start),
      .din   (din),
      .state (st[i]),
      .dout  (lane_out[i])
    );
  end

  crc8 u_crc (.data(lane_out[0]), .crc(crc));

  always_ff @(posedge clk) begin
    if (st[0] == DONE) mem[wptr] <= lane_out[0];
  end

  assign hdr.payload = mem[0];
  assign hdr.len     = 3'd4;
  assign hdr.last    = (st[1] == DONE);
  assign hdr_out     = hdr;
  assign sum         = {8'h00, lane_out[0]} + {8'h00, lane_out[1]} + {8'h00, crc};

  assert property (@(posedge clk) disable iff (!rst_n) !$isunknown(st[0]));
endmodule

samples/sdi/tb.sv
// Testbench for the SDI sample. Exists to produce `gate.vcd`, whose scope and
// leaf names the SDI binding rules are checked against.
module tb;
  logic        clk = 1'b0;
  logic        rst_n = 1'b0;
  logic        start = 1'b0;
  logic [7:0]  din = 8'h00;
  logic [1:0]  wptr = 2'd0;
  logic [15:0] sum;
  logic [11:0] hdr_out;

  gate dut (
    .clk (clk), .rst_n (rst_n), .start (start), .din (din),
    .wptr (wptr), .sum (sum), .hdr_out (hdr_out)
  );

  always #5 clk = ~clk;

  initial begin
    $dumpfile("gate.vcd");
    $dumpvars(0, tb);
    #12 rst_n = 1'b1;
    din = 8'h21;
    for (int c = 0; c < 8; c++) begin
      @(posedge clk);
      start <= (c % 3 == 0);
      wptr  <= c[1:0];
      din   <= din + 8'h11;
    end
    #20 $finish;
  end
endmodule

samples/sdi/gate.vcd
$date
	Thu Jul 30 23:02:26 2026
$end
$version
	Icarus Verilog
$end
$timescale
	1s
$end
$scope module tb $end
$var wire 16 ! sum [15:0] $end
$var wire 12 " hdr_out [11:0] $end
$var reg 1 # clk $end
$var reg 8 $ din [7:0] $end
$var reg 1 % rst_n $end
$var reg 1 & start $end
$var reg 2 ' wptr [1:0] $end
$scope module dut $end
$var wire 1 # clk $end
$var wire 8 ( din [7:0] $end
$var wire 12 ) hdr_out [11:0] $end
$var wire 1 % rst_n $end
$var wire 1 & start $end
$var wire 2 * wptr [1:0] $end
$var wire 16 + sum [15:0] $end
$var wire 12 , hdr [11:0] $end
$var wire 8 - crc [7:0] $end
$scope begin g_lane[0] $end
$var parameter 2 . i $end
$scope module u_lane $end
$var wire 1 # clk $end
$var wire 8 / din [7:0] $end
$var wire 8 0 dout [7:0] $end
$var wire 1 % rst_n $end
$var wire 1 & start $end
$var parameter 32 1 W $end
$var reg 8 2 acc [7:0] $end
$var reg 2 3 nxt [1:0] $end
$var reg 2 4 state [1:0] $end
$upscope $end
$upscope $end
$scope begin g_lane[1] $end
$var parameter 2 5 i $end
$scope module u_lane $end
$var wire 1 # clk $end
$var wire 8 6 din [7:0] $end
$var wire 8 7 dout [7:0] $end
$var wire 1 % rst_n $end
$var wire 1 & start $end
$var parameter 32 8 W $end
$var reg 8 9 acc [7:0] $end
$var reg 2 : nxt [1:0] $end
$var reg 2 ; state [1:0] $end
$upscope $end
$upscope $end
$scope module u_crc $end
$var wire 8 < crc [7:0] $end
$var wire 8 = data [7:0] $end
$upscope $end
$upscope $end
$scope begin $ivl_for_loop0 $end
$var integer 32 > c [31:0] $end
$upscope $end
$upscope $end
$enddefinitions $end
$comment Show the parameter values. $end
$dumpall
b1000 8
b1 5
b1000 1
b0 .
$end
#0
$dumpvars
b0 >
bx =
bx <
bx ;
bx :
bx 9
bx 7
b0 6
bx 4
bx 3
bx 2
bx 0
b0 /
bx -
bx100x ,
bx +
b0 *
bx100x )
b0 (
b0 '
0&
0%
b0 $
0#
bx100x "
bx !
$end
#5
b0 3
b0 :
bx1000 "
bx1000 )
bx1000 ,
b0 4
b0 ;
1#
#10
0#
#12
b100001 $
b100001 (
b100001 /
b100001 6
1%
#15
b1 3
b1 :
b110010 $
b110010 (
b110010 /
b110010 6
1&
b1 >
1#
#20
0#
#25
b11 3
b11 :
b1 4
b1 ;
b1000011 $
b1000011 (
b1000011 /
b1000011 6
b1 '
b1 *
0&
b10 >
1#
#30
0#
#35
b0 :
bx1001 "
bx1001 )
bx1001 ,
b0 3
b11 ;
b11 4
b1010100 $
b1010100 (
b1010100 /
b1010100 6
b10 '
b10 *
b11 >
1#
#40
0#
#45
bx1000 "
bx1000 )
bx1000 ,
b1 3
b1 :
b0 4
b0 ;
b1100101 $
b1100101 (
b1100101 /
b1100101 6
b11 '
b11 *
1&
b100 >
1#
#50
0#
#55
b11 3
b11 :
b1 ;
b1 4
b1110110 $
b1110110 (
b1110110 /
b1110110 6
b0 '
b0 *
0&
b101 >
1#
#60
0#
#65
b0 3
b0 :
bx1001 "
bx1001 )
bx1001 ,
b11 4
b11 ;
b10000111 $
b10000111 (
b10000111 /
b10000111 6
b1 '
b1 *
b110 >
1#
#70
0#
#75
bx1000 "
bx1000 )
bx1000 ,
b1 3
b1 :
b0 ;
b0 4
b10011000 $
b10011000 (
b10011000 /
b10011000 6
b10 '
b10 *
1&
b111 >
1#
#80
0#
#85
b11 3
b11 :
b1 4
b1 ;
b10101001 $
b10101001 (
b10101001 /
b10101001 6
b11 '
b11 *
0&
b1000 >
1#
#90
0#
#95
b0 :
bx1001 "
bx1001 )
bx1001 ,
b0 3
b11 ;
b11 4
1#
#100
0#
#105
bx1000 "
bx1000 )
bx1000 ,
b0 4
b0 ;
1#
